StatTools/Gamma.py
StatTools/__init__.py
StatTools/_version.py
StatTools/auxiliary.py
StatTools/analysis/__init__.py
StatTools/analysis/dfa.py
StatTools/analysis/dpcca.py
StatTools/analysis/dpcca_as_class.py
StatTools/analysis/fa.py
StatTools/analysis/movmean.py
StatTools/analysis/nd_dfa.py
StatTools/analysis/qss.py
StatTools/analysis/support_ff.py
StatTools/analysis/svd_dfa.py
StatTools/analysis/utils.py
StatTools/analysis/nonequidistant/__init__.py
StatTools/analysis/nonequidistant/dfa.py
StatTools/experimental/__init__.py
StatTools/experimental/analysis/__init__.py
StatTools/experimental/analysis/tools.py
StatTools/experimental/augmentation/__init__.py
StatTools/experimental/augmentation/perturbations.py
StatTools/experimental/synthesis/__init__.py
StatTools/experimental/synthesis/tools.py
StatTools/filters/kalman_filter.py
StatTools/filters/symbolic_kalman.py
StatTools/generators/__init__.py
StatTools/generators/base_filter.py
StatTools/generators/cholesky_transform.py
StatTools/generators/fbm.py
StatTools/generators/field_generator.py
StatTools/generators/kasdin_generator.py
StatTools/generators/lbfbm_generator.py
StatTools/generators/ndfnoise_generator.py
StatTools/native/.gitkeep
StatTools/native/C_StatTools.cp311-win_amd64.pyd
StatTools/native/StatTools_bindings.cp311-win_amd64.pyd
StatTools/utilities/deprecation.py
StatTools/visualization/__init__.py
StatTools/visualization/plot_ff.py
fluctuationanalysistools-1.10.0.dist-info/licenses/LICENSE.txt
fluctuationanalysistools-1.10.0.dist-info/METADATA
fluctuationanalysistools-1.10.0.dist-info/WHEEL
fluctuationanalysistools-1.10.0.dist-info/top_level.txt
fluctuationanalysistools-1.10.0.dist-info/RECORD
