Metadata-Version: 2.4
Name: FluctuationAnalysisTools
Version: 1.10.0
Summary: Python library for DFA, Hurst exponent, and fluctuation analysis of time series.
Author: Maya Gavrichenkova, Timofey Baburin, Olga Ivleva
Author-email: Aleksandr Sinitca <amsinitca@etu.ru>, Alexandr Kuzmenko <alexander.k.spb@gmail.com>, Asya Lyanova <ailianova@etu.ru>
Maintainer-email: Aleksandr Sinitca <amsinitca@etu.ru>
License: MIT
Project-URL: Repository, https://github.com/Digiratory/FluctuationAnalysisTools.git
Project-URL: Issues, https://github.com/Digiratory/FluctuationAnalysisTools/issues
Project-URL: Changelog, https://github.com/Digiratory/FluctuationAnalysisTools/blob/main/CHANGELOG.md
License-File: LICENSE.txt
Requires-Dist: numpy>=1.22.4
Requires-Dist: psutil==5.8.0
Requires-Dist: scipy>=1.13.1
Requires-Dist: setuptools>=70.0.0
Requires-Dist: tqdm~=4.62.3
Requires-Dist: pandas>=1.3.5
Requires-Dist: filterpy>=1.4.5
Requires-Dist: sympy>=1.14.0
Requires-Dist: pybind11>=2.11.1
Dynamic: license-file
